konichiha/__init__.py
konichiha/main.py
tests/__init__.py
tests/test_main.py
konichiha-0.7.0.dist-info/METADATA
konichiha-0.7.0.dist-info/WHEEL
konichiha-0.7.0.dist-info/top_level.txt
konichiha-0.7.0.dist-info/RECORD
